progiclone/__init__.py
progiclone/main.py
progiclone-1.1.0.dist-info/METADATA
progiclone-1.1.0.dist-info/WHEEL
progiclone-1.1.0.dist-info/entry_points.txt
progiclone-1.1.0.dist-info/top_level.txt
progiclone-1.1.0.dist-info/RECORD
