Metadata-Version: 2.2
Name: progiclone
Version: 1.1.0
Summary: Outil d'anonymisation des données sécurisé pour Dolibarr
Home-page: https://github.com/valent1d/progiclone
Author: VLTN x Progiseize
Author-email: v.denis@progiseize.fr
Keywords: dolibarr anonymization database mysql ssh security gdpr
Classifier: Programming Language :: Python :: 3
Classifier: License :: OSI Approved :: MIT License
Classifier: Operating System :: OS Independent
Classifier: Development Status :: 5 - Production/Stable
Classifier: Intended Audience :: Developers
Classifier: Intended Audience :: System Administrators
Classifier: Topic :: Database
Classifier: Topic :: Security
Classifier: Topic :: Utilities
Requires-Python: >=3.7
Requires-Dist: pyfiglet
Requires-Dist: tqdm
Requires-Dist: Faker
Requires-Dist: mysql-connector-python
Requires-Dist: requests
Requires-Dist: PyYAML
Requires-Dist: argparse
Requires-Dist: sshtunnel
Dynamic: author
Dynamic: author-email
Dynamic: classifier
Dynamic: description
Dynamic: description-content-type
Dynamic: home-page
Dynamic: keywords
Dynamic: requires-dist
Dynamic: requires-python
Dynamic: summary
